README.rst
ingestor.py
setup.cfg
setup.py
threadedSearch.py
DIY_FilingsResearch.egg-info/PKG-INFO
DIY_FilingsResearch.egg-info/SOURCES.txt
DIY_FilingsResearch.egg-info/dependency_links.txt
DIY_FilingsResearch.egg-info/requires.txt
DIY_FilingsResearch.egg-info/top_level.txt
examples/download_edgar.py
examples/download_sedar.py
examples/searcher.py