Metadata-Version: 1.1
Name: DIY-FilingsResearch
Version: 0.2.0
Summary: library for analyzing company financial documents
Home-page: https://github.com/greedo/DIY-FilingsResearch/
Author: Joe Cabrera
Author-email: jcabrera@eminorlabs.com
License: Apache License
Keywords: Financial,Accounting,file formats,10k,10q,filings,edgar,sedar
Platform: UNKNOWN
Classifier: Intended Audience :: Developers
Classifier: Natural Language :: English
Classifier: Operating System :: OS Independent
Classifier: Programming Language :: Python :: 3.4
Classifier: Programming Language :: Python :: 3.3
Classifier: Programming Language :: Python :: 2.7
Classifier: Topic :: Software Development :: Libraries :: Python Modules
Classifier: Topic :: Office/Business :: Financial
